Littledog_LittleDog5727/__init__.py
Littledog_LittleDog5727/module.py
Littledog_LittleDog5727-0.0.4.dist-info/LICENSE
Littledog_LittleDog5727-0.0.4.dist-info/METADATA
Littledog_LittleDog5727-0.0.4.dist-info/WHEEL
Littledog_LittleDog5727-0.0.4.dist-info/top_level.txt
Littledog_LittleDog5727-0.0.4.dist-info/RECORD
