Metadata-Version: 2.1
Name: Littledog-LittleDog5727
Version: 0.0.4
Summary: A small package
Author-email: Little Dog <littledog.5727@gmail.com>
Classifier: Programming Language :: Python :: 3
Classifier: License :: OSI Approved :: MIT License 
Classifier: Operating System :: OS Independent
Requires-Python: >=3.7
License-File: LICENSE
